RASST/__init__.py
RASST/__main__.py
RASST/altimetry.py
RASST/datahandler.py
RASST/debug.py
RASST/georaster.py
RASST/model.py
RASST/waveform.py
rasst-0.0.2.dist-info/METADATA
rasst-0.0.2.dist-info/WHEEL
rasst-0.0.2.dist-info/licenses/LICENSE.md
rasst-0.0.2.dist-info/RECORD
