Metadata-Version: 2.1
Name: RASST
Version: 0.0.2
Summary: Radar Altimeter Source Separation Toolbox
Project-URL: Homepage, https://github.com/BjarkeN/RASST
Author-email: Bjarke Nilsson <s180866@student.dtu.dk>
License-File: LICENSE.md
Classifier: License :: OSI Approved :: MIT License
Classifier: Operating System :: OS Independent
Classifier: Programming Language :: Python :: 3
Requires-Python: >=3.8.8
